[
    {
        "Id": 1,
        "GitHubFileId": "01JDEF9N5PBC2GZ7QPRJGM9K5D",
        "Events": []
    },
    {
        "Id": 2,
        "GitHubFileId": "01JDEF9N6E8D2V2HGJDTJNMVDE",
        "Events": []
    },
    {
        "Id": 3,
        "GitHubFileId": "01JDEF9N6EQT354YFPZW83ZNYY",
        "Events": []
    },
    {
        "Id": 4,
        "GitHubFileId": "01JDEF9N6E7ATJX8CSM6MR819W",
        "Events": []
    },
    {
        "Id": 5,
        "GitHubFileId": "01JDEF9N6EPP953MZ16A23QA2J",
        "Events": []
    },
    {
        "Id": 6,
        "GitHubFileId": "01JDEF9N6EXHZTH0QT1CQE1JAX",
        "Events": []
    },
    {
        "Id": 7,
        "GitHubFileId": "01JDEF9N6E8E5NDA746EG6QN8B",
        "Events": []
    },
    {
        "Id": 8,
        "GitHubFileId": "01JDEF9N6E2XDQYVH780B768B9",
        "Events": []
    },
    {
        "Id": 9,
        "GitHubFileId": "01JDEF9N6ETYCYWJ3ZMDKEXYRB",
        "Events": []
    },
    {
        "Id": 10,
        "GitHubFileId": "01JDEF9N6EE59C957AW2GVNZ6D",
        "Events": []
    },
    {
        "Id": 11,
        "GitHubFileId": "01JDEF9N6EQWK86HBXEN7BNMQF",
        "Events": []
    },
    {
        "Id": 12,
        "GitHubFileId": "01JDEF9N6ER5NR9K6SDN0ZFGA0",
        "Events": []
    },
    {
        "Id": 13,
        "GitHubFileId": "01JDEF9N6E8C8HP2ZNENST659N",
        "Events": []
    },
    {
        "Id": 14,
        "GitHubFileId": "01JDEF9N6EV0ZF2HNGD1YAJQKJ",
        "Events": []
    },
    {
        "Id": 15,
        "GitHubFileId": "01JDEF9N6EXSVTW66R2N80A2PF",
        "Events": []
    },
    {
        "Id": 16,
        "GitHubFileId": "01JDEF9N6EH6JKJ77TJERN7NTW",
        "Events": []
    },
    {
        "Id": 17,
        "GitHubFileId": "01JDEF9N6EQ5X2N697V50XBFC5",
        "Events": []
    },
    {
        "Id": 18,
        "GitHubFileId": "01JDEF9N6ENHWZP5NFAWSXYSQ6",
        "Events": []
    },
    {
        "Id": 19,
        "GitHubFileId": "01JDEF9N6E9SWJ3WN722S9XC34",
        "Events": []
    },
    {
        "Id": 20,
        "GitHubFileId": "01JDEF9N6ET16G4JC9X9E8M6TC",
        "Events": []
    },
    {
        "Id": 21,
        "GitHubFileId": "01JDEF9N6EWVF30SZPJHESQ15Y",
        "Events": []
    },
    {
        "Id": 22,
        "GitHubFileId": "01JDEF9N6ESWEK4S52Y9T5GK57",
        "Events": []
    },
    {
        "Id": 23,
        "GitHubFileId": "01JDEF9N6E1JTSBZMS6A44GMDH",
        "Events": []
    },
    {
        "Id": 24,
        "GitHubFileId": "01JDEF9N6E9Y3XYB9QKKS7RW75",
        "Events": []
    },
    {
        "Id": 25,
        "GitHubFileId": "01JDEF9N6EQR91GE5ZC5P6AHZD",
        "Events": []
    },
    {
        "Id": 26,
        "GitHubFileId": "01JDEF9N6EG8JZ1MZSP02B1597",
        "Events": []
    },
    {
        "Id": 27,
        "GitHubFileId": "01JDEF9N6EWMHRTRGBWFFGX2BG",
        "Events": []
    },
    {
        "Id": 28,
        "GitHubFileId": "01JDEF9N6E3XWP8V1FGV97ME1Y",
        "Events": []
    },
    {
        "Id": 29,
        "GitHubFileId": "01JDEF9N6ESE930EZ0DDX96218",
        "Events": []
    },
    {
        "Id": 30,
        "GitHubFileId": "01JDEF9N6EW5EKF8JCWYVRNMR7",
        "Events": []
    },
    {
        "Id": 31,
        "GitHubFileId": "01JDEF9N6EDCVTMM8RACXRNRYY",
        "Events": []
    },
    {
        "Id": 32,
        "GitHubFileId": "01JDEF9N6EX0E5S06D23K93Y0Q",
        "Events": []
    },
    {
        "Id": 33,
        "GitHubFileId": "01JDEF9N6EHEM7VQ5F6MTNJ709",
        "Events": []
    },
    {
        "Id": 34,
        "GitHubFileId": "01JDEF9N6E1K1EWB57GY5D7G9Y",
        "Events": []
    },
    {
        "Id": 35,
        "GitHubFileId": "01JDEF9N6E8D1V4ZR4J3NT1A2X",
        "Events": []
    },
    {
        "Id": 36,
        "GitHubFileId": "01JDEF9N6EC6XP8Q6J3T75K0TQ",
        "Events": []
    },
    {
        "Id": 37,
        "GitHubFileId": "01JDEF9N6EAE80ZZJ5QS13WWN4",
        "Events": []
    },
    {
        "Id": 38,
        "GitHubFileId": "01JDEF9N6EYEJ1VKNJCMNHQW8C",
        "Events": []
    },
    {
        "Id": 39,
        "GitHubFileId": "01JDEF9N6EFPNBEYX44V4N0DAQ",
        "Events": []
    },
    {
        "Id": 40,
        "GitHubFileId": "01JDEF9N6EWZPAHD8HZTGSJ7HG",
        "Events": []
    },
    {
        "Id": 41,
        "GitHubFileId": "01JDEF9N6E3021SMFJ5AW07WCS",
        "Events": []
    },
    {
        "Id": 42,
        "GitHubFileId": "01JDEF9N6E6E9FDXQMBH1KY4Y1",
        "Events": []
    },
    {
        "Id": 43,
        "GitHubFileId": "01JDEF9N6E635DKVJPKF7EQJGW",
        "Events": []
    },
    {
        "Id": 44,
        "GitHubFileId": "01JDEF9N6EK29FESN6EEAP8DNR",
        "Events": []
    },
    {
        "Id": 45,
        "GitHubFileId": "01JDEF9N6EZ5BJS7044GW711R9",
        "Events": []
    },
    {
        "Id": 46,
        "GitHubFileId": "01JDEF9N6ED6QY9Q21BNDGR477",
        "Events": []
    },
    {
        "Id": 47,
        "GitHubFileId": "01JDEF9N6E6DWM65NTKG5252ZZ",
        "Events": []
    },
    {
        "Id": 48,
        "GitHubFileId": "01JDEF9N6EB3QQKM33F3KCH3HS",
        "Events": []
    },
    {
        "Id": 49,
        "GitHubFileId": "01JDEF9N6E1WMNGCY2B49V8A5M",
        "Events": []
    },
    {
        "Id": 50,
        "GitHubFileId": "01JDEF9N6EJZS4QHMCSMM48E5H",
        "Events": []
    },
    {
        "Id": 51,
        "GitHubFileId": "01JDEF9N6E78A3XYECC53XYDXB",
        "Events": []
    },
    {
        "Id": 52,
        "GitHubFileId": "01JDEF9N6E1PZD2VJEVR6H1R2G",
        "Events": []
    },
    {
        "Id": 53,
        "GitHubFileId": "01JDEF9N6ETAXBQFRXKJK75STW",
        "Events": []
    },
    {
        "Id": 54,
        "GitHubFileId": "01JDEF9N6E181MJ0WV8TS3BJWB",
        "Events": []
    },
    {
        "Id": 55,
        "GitHubFileId": "01JDEF9N6EK8NAJRJCDYYQAAJX",
        "Events": []
    },
    {
        "Id": 56,
        "GitHubFileId": "01JDEF9N6EPA45NFVX7HZHWQ7J",
        "Events": []
    },
    {
        "Id": 57,
        "GitHubFileId": "01JDEF9N6EAD1TCAZKMW86SP62",
        "Events": []
    },
    {
        "Id": 58,
        "GitHubFileId": "01JDEF9N6EVB5WKC31FJDV6JFJ",
        "Events": []
    },
    {
        "Id": 59,
        "GitHubFileId": "01JDEF9N6EME4CYD3KSCM8PDDB",
        "Events": []
    },
    {
        "Id": 60,
        "GitHubFileId": "01JDEF9N6EWRKGSX9XX25RQYE5",
        "Events": []
    },
    {
        "Id": 61,
        "GitHubFileId": "01JDEF9N6EPM811M0Z9515G759",
        "Events": []
    },
    {
        "Id": 62,
        "GitHubFileId": "01JDEF9N6EZJHN5FWTHZ32B25P",
        "Events": []
    },
    {
        "Id": 63,
        "GitHubFileId": "01JDEF9N6EV5T5ADY687FEJSW3",
        "Events": []
    },
    {
        "Id": 64,
        "GitHubFileId": "01JDEF9N6E3FSJ913RTBNPE5KN",
        "Events": []
    },
    {
        "Id": 65,
        "GitHubFileId": "01JDEF9N6EDY5Z3Y5CTX76GWYK",
        "Events": []
    },
    {
        "Id": 66,
        "GitHubFileId": "01JDEF9N6E65M8KGQSVVYSZV8K",
        "Events": []
    },
    {
        "Id": 67,
        "GitHubFileId": "01JDEF9N6E9A51TTAB2H3QA3JD",
        "Events": []
    },
    {
        "Id": 68,
        "GitHubFileId": "01JDEF9N6EDRCFJPGS491C9HQ2",
        "Events": []
    },
    {
        "Id": 69,
        "GitHubFileId": "01JDEF9N6ED9YCW1WPWWRNHHKK",
        "Events": []
    },
    {
        "Id": 70,
        "GitHubFileId": "01JDEF9N6E7TN697GGXTK1HP61",
        "Events": []
    },
    {
        "Id": 71,
        "GitHubFileId": "01JDEF9N6EPA1HYB21M7F15X6C",
        "Events": []
    },
    {
        "Id": 72,
        "GitHubFileId": "01JDEF9N6E1V4EJNQ50JF4HNF5",
        "Events": []
    },
    {
        "Id": 73,
        "GitHubFileId": "01JDEF9N6EF02T9GHPWDDJ8WXM",
        "Events": []
    },
    {
        "Id": 74,
        "GitHubFileId": "01JDEF9N6EDJXPMNNT4K7M6X2Y",
        "Events": []
    },
    {
        "Id": 75,
        "GitHubFileId": "01JDEF9N6EVENQHEMRAD01K2TQ",
        "Events": []
    },
    {
        "Id": 76,
        "GitHubFileId": "01JDEF9N6EQDJ2E9BFQV86JJDN",
        "Events": []
    },
    {
        "Id": 77,
        "GitHubFileId": "01JDEF9N6EFH4CEE5M4T27TFZB",
        "Events": []
    },
    {
        "Id": 78,
        "GitHubFileId": "01JDEF9N6ED87VFCMFPMZFJM19",
        "Events": []
    },
    {
        "Id": 79,
        "GitHubFileId": "01JDEF9N6E8F1B491NHJD523SQ",
        "Events": []
    },
    {
        "Id": 80,
        "GitHubFileId": "01JDEF9N6E1GQ9GNDWQ56WMZYF",
        "Events": []
    },
    {
        "Id": 81,
        "GitHubFileId": "01JDEF9N6ETH9CHZPJGNCTQRH1",
        "Events": []
    },
    {
        "Id": 82,
        "GitHubFileId": "01JDEF9N6E0Q665C7B13GEGBNZ",
        "Events": []
    },
    {
        "Id": 83,
        "GitHubFileId": "01JDEF9N6EM8C0D2A5BTFYP4RF",
        "Events": []
    },
    {
        "Id": 84,
        "GitHubFileId": "01JDEF9N6EGD50D1G76DSW2S6M",
        "Events": []
    },
    {
        "Id": 85,
        "GitHubFileId": "01JDEF9N6E8KKYDCQAT6YF996X",
        "Events": []
    },
    {
        "Id": 86,
        "GitHubFileId": "01JDEF9N6E0TCCQBB2HQJ3G2Q3",
        "Events": []
    },
    {
        "Id": 87,
        "GitHubFileId": "01JDEF9N6EDX95TS7ZW3RC1FVM",
        "Events": []
    },
    {
        "Id": 88,
        "GitHubFileId": "01JDEF9N6EF3P11TPVRZQSJ1ME",
        "Events": []
    },
    {
        "Id": 89,
        "GitHubFileId": "01JDEF9N6EC7TM79ASCW3E4V0B",
        "Events": []
    },
    {
        "Id": 90,
        "GitHubFileId": "01JDEF9N6E870Z2SQXA0NZFYGW",
        "Events": []
    },
    {
        "Id": 91,
        "GitHubFileId": "01JDEF9N6EFRWVT94405C0PF5S",
        "Events": []
    },
    {
        "Id": 92,
        "GitHubFileId": "01JDEF9N6E02RSG9K5HB1YAVNJ",
        "Events": []
    },
    {
        "Id": 93,
        "GitHubFileId": "01JDEF9N6ENM8MX5GN8AERA3HA",
        "Events": []
    },
    {
        "Id": 94,
        "GitHubFileId": "01JDEF9N6E2VFFR7Y0AB17EV40",
        "Events": []
    },
    {
        "Id": 95,
        "GitHubFileId": "01JDEF9N6E1J3CS2Q3DMAG82NG",
        "Events": []
    },
    {
        "Id": 96,
        "GitHubFileId": "01JDEF9N6EQBZJQTCBB0QD668W",
        "Events": []
    },
    {
        "Id": 97,
        "GitHubFileId": "01JDEF9N6E2Q1V20C26CW5ZM3C",
        "Events": []
    },
    {
        "Id": 98,
        "GitHubFileId": "01JDEF9N6EBPC0CV8R4WFWT7KT",
        "Events": []
    },
    {
        "Id": 99,
        "GitHubFileId": "01JDEF9N6EE5WH38KFFP7VCNYM",
        "Events": []
    },
    {
        "Id": 100,
        "GitHubFileId": "01JDEF9N6ERKTMZHWYHYMTETR6",
        "Events": []
    },
    {
        "Id": 101,
        "GitHubFileId": "01JDEF9N6EFWFEZ22Y9YQBY1Z3",
        "Events": []
    },
    {
        "Id": 102,
        "GitHubFileId": "01JDEF9N6E23SETCVVWS12ZR0M",
        "Events": []
    },
    {
        "Id": 103,
        "GitHubFileId": "01JDEF9N6E1WT1CY9Q1W812F06",
        "Events": []
    },
    {
        "Id": 104,
        "GitHubFileId": "01JDEF9N6EXYVMZ3E5TN1H4YR4",
        "Events": []
    },
    {
        "Id": 105,
        "GitHubFileId": "01JDEF9N6EBANXKR2T9W4DFV6E",
        "Events": []
    },
    {
        "Id": 106,
        "GitHubFileId": "01JDEF9N6E3YCH87AV8RAZMEEN",
        "Events": []
    },
    {
        "Id": 107,
        "GitHubFileId": "01JDEF9N6EVXYHDZFYNDP83DDS",
        "Events": []
    },
    {
        "Id": 108,
        "GitHubFileId": "01JDEF9N6E5MV3VE2ZQVMDTRP1",
        "Events": []
    },
    {
        "Id": 109,
        "GitHubFileId": "01JDEF9N6EDSKGCB6FDKWYY5KA",
        "Events": []
    },
    {
        "Id": 110,
        "GitHubFileId": "01JDEF9N6EJ61V81FWHAR81S69",
        "Events": []
    },
    {
        "Id": 111,
        "GitHubFileId": "01JDEF9N6EVEG3VSRJMDYXGKZ7",
        "Events": []
    },
    {
        "Id": 112,
        "GitHubFileId": "01JDEF9N6E054YBRFK6VPV8P01",
        "Events": []
    },
    {
        "Id": 113,
        "GitHubFileId": "01JDEF9N6EXJ91XMPY614Q4XG7",
        "Events": []
    },
    {
        "Id": 114,
        "GitHubFileId": "01JDEF9N6EY034ZWY6HE3SHWXM",
        "Events": []
    },
    {
        "Id": 115,
        "GitHubFileId": "01JDEF9N6ECM5VKFM8N71EXJV1",
        "Events": []
    },
    {
        "Id": 116,
        "GitHubFileId": "01JDEF9N6ES04KXQREAWZE4TXV",
        "Events": []
    },
    {
        "Id": 117,
        "GitHubFileId": "01JDEF9N6EKSR029SYZM2AESA0",
        "Events": []
    },
    {
        "Id": 118,
        "GitHubFileId": "01JDEF9N6EAARNXEQCA8HD4AHN",
        "Events": []
    },
    {
        "Id": 119,
        "GitHubFileId": "01JDEF9N6EJK6HESEXXQRPDDN9",
        "Events": []
    },
    {
        "Id": 120,
        "GitHubFileId": "01JDEF9N6EC1CH827S6E25311C",
        "Events": []
    },
    {
        "Id": 121,
        "GitHubFileId": "01JDEF9N6EJPY6X5524S1S6T13",
        "Events": []
    },
    {
        "Id": 122,
        "GitHubFileId": "01JDEF9N6E7XBXQX03JM2SPAH2",
        "Events": []
    },
    {
        "Id": 123,
        "GitHubFileId": "01JDEF9N6EJZJR0VN4JXZHYVC9",
        "Events": []
    },
    {
        "Id": 124,
        "GitHubFileId": "01JDEF9N6E2ZKT3KD168X0JDE1",
        "Events": []
    },
    {
        "Id": 125,
        "GitHubFileId": "01JDEF9N6ENWZ9P7DDM16EBW4N",
        "Events": []
    },
    {
        "Id": 126,
        "GitHubFileId": "01JDEF9N6EYF0PY94J2H7PDBNQ",
        "Events": []
    },
    {
        "Id": 127,
        "GitHubFileId": "01JDEF9N6EWV9QC0TKYQJAGC9P",
        "Events": []
    },
    {
        "Id": 128,
        "GitHubFileId": "01JDEF9N6E5B8GH3Q222S453AQ",
        "Events": []
    },
    {
        "Id": 129,
        "GitHubFileId": "01JDEF9N6ESNCD48P2R91CECS3",
        "Events": []
    },
    {
        "Id": 130,
        "GitHubFileId": "01JDEF9N6EEYH3PC4AJX506X7W",
        "Events": []
    },
    {
        "Id": 131,
        "GitHubFileId": "01JDEF9N6ENNJB9XHEPA0NJFPD",
        "Events": []
    },
    {
        "Id": 132,
        "GitHubFileId": "01JDEF9N6EC837JXE1GBEP7N2F",
        "Events": []
    },
    {
        "Id": 133,
        "GitHubFileId": "01JDEF9N6E3QTE0GJ43YJSCDVY",
        "Events": []
    },
    {
        "Id": 134,
        "GitHubFileId": "01JDEF9N6EF602EGD1QE9QF4M2",
        "Events": []
    },
    {
        "Id": 135,
        "GitHubFileId": "01JDEF9N6E9S9F8YXP9PKDXVSD",
        "Events": []
    },
    {
        "Id": 136,
        "GitHubFileId": "01JDEF9N6E6K25Q3SS81D3QQFC",
        "Events": []
    },
    {
        "Id": 137,
        "GitHubFileId": "01JDEF9N6ES9ESCHSTS7BC76W2",
        "Events": []
    },
    {
        "Id": 138,
        "GitHubFileId": "01JDEF9N6EA2089MDSRG1TVXT1",
        "Events": []
    },
    {
        "Id": 139,
        "GitHubFileId": "01JDEF9N6E1MXX7FEKCY03C844",
        "Events": []
    },
    {
        "Id": 140,
        "GitHubFileId": "01JDEF9N6EZ59EWQVTGCA8V4NC",
        "Events": []
    },
    {
        "Id": 141,
        "GitHubFileId": "01JDEF9N6E7A1FAPQKZWZJXJSP",
        "Events": []
    },
    {
        "Id": 142,
        "GitHubFileId": "01JDEF9N6ECM7VQM1Y3P9AXKQ9",
        "Events": []
    },
    {
        "Id": 143,
        "GitHubFileId": "01JDEF9N6EFPKB2YK74D3ZKTT1",
        "Events": []
    },
    {
        "Id": 144,
        "GitHubFileId": "01JDEF9N6E417WZ1DCE5R9XB4J",
        "Events": []
    },
    {
        "Id": 145,
        "GitHubFileId": "01JDEF9N6EFTAYQ4ASE1BJYA44",
        "Events": []
    },
    {
        "Id": 146,
        "GitHubFileId": "01JDEF9N6EV4PFJ57KD2ZD1VXB",
        "Events": []
    },
    {
        "Id": 147,
        "GitHubFileId": "01JDEF9N6ESQA99ZVDQXSDVJT8",
        "Events": []
    },
    {
        "Id": 148,
        "GitHubFileId": "01JDEF9N6EHVYD73S23H6DV4NM",
        "Events": []
    },
    {
        "Id": 149,
        "GitHubFileId": "01JDEF9N6EW3A34R27S6T5NQHW",
        "Events": []
    },
    {
        "Id": 150,
        "GitHubFileId": "01JDEF9N6EHR12S93JSDWG5YDY",
        "Events": []
    },
    {
        "Id": 151,
        "GitHubFileId": "01JDEF9N6EEPHBKZ2GQRY0ZZYE",
        "Events": []
    },
    {
        "Id": 152,
        "GitHubFileId": "01JDEF9N6ED6VYH72MH7J269H1",
        "Events": []
    },
    {
        "Id": 153,
        "GitHubFileId": "01JDEF9N6EKHJMKXR2DV36PJC5",
        "Events": []
    },
    {
        "Id": 154,
        "GitHubFileId": "01JDEF9N6EC3QWY0Y1XYMCFF6Q",
        "Events": []
    },
    {
        "Id": 155,
        "GitHubFileId": "01JDEF9N6E7N211T14236WANZ4",
        "Events": []
    },
    {
        "Id": 156,
        "GitHubFileId": "01JDEF9N6EC349SRJH1A6M9F96",
        "Events": []
    },
    {
        "Id": 157,
        "GitHubFileId": "01JDEF9N6ESBY0DFKGYFZ1Q4B9",
        "Events": []
    },
    {
        "Id": 158,
        "GitHubFileId": "01JDEF9N6EV0N7Q29SEQWTRYG7",
        "Events": []
    },
    {
        "Id": 159,
        "GitHubFileId": "01JDEF9N6EC759S30A5EK9NMW2",
        "Events": []
    },
    {
        "Id": 160,
        "GitHubFileId": "01JDEF9N6EZQJB1BHM1HX4KSTY",
        "Events": []
    },
    {
        "Id": 161,
        "GitHubFileId": "01JDEF9N6E9F3QMSR5ANCPKF47",
        "Events": []
    },
    {
        "Id": 162,
        "GitHubFileId": "01JDEF9N6E2W0N5S6XGDH1QRCB",
        "Events": []
    },
    {
        "Id": 163,
        "GitHubFileId": "01JDEF9N6EPHDB86HCJKDWHDPK",
        "Events": []
    },
    {
        "Id": 164,
        "GitHubFileId": "01JDEF9N6E2H83JFQNK6R3B0B3",
        "Events": []
    },
    {
        "Id": 165,
        "GitHubFileId": "01JDEF9N6EN2BRJ2W8J9V5GY86",
        "Events": []
    },
    {
        "Id": 166,
        "GitHubFileId": "01JDEF9N6EXT4X2VTZNZ6THRTY",
        "Events": []
    },
    {
        "Id": 167,
        "GitHubFileId": "01JDEF9N6E2BSTZCKD8GQ2WNDZ",
        "Events": []
    },
    {
        "Id": 168,
        "GitHubFileId": "01JDEF9N6EBPZXAE0BGW105Q7H",
        "Events": []
    },
    {
        "Id": 169,
        "GitHubFileId": "01JDEF9N6EZGCRYTPEC6BNZQZP",
        "Events": []
    },
    {
        "Id": 170,
        "GitHubFileId": "01JDEF9N6EK581F54MBAN8YA87",
        "Events": []
    },
    {
        "Id": 171,
        "GitHubFileId": "01JDEF9N6EV3R9D2YJQ4ZM0MA0",
        "Events": []
    },
    {
        "Id": 172,
        "GitHubFileId": "01JDEF9N6E6R5QXKD5P1EAMMRA",
        "Events": []
    },
    {
        "Id": 173,
        "GitHubFileId": "01JDEF9N6ERX9SYFB7W92FWG78",
        "Events": []
    },
    {
        "Id": 174,
        "GitHubFileId": "01JDEF9N6EWR7DHDNQBGMZ7J75",
        "Events": []
    },
    {
        "Id": 175,
        "GitHubFileId": "01JDEF9N6EPNPAX6G0312940PS",
        "Events": []
    },
    {
        "Id": 176,
        "GitHubFileId": "01JDEF9N6E93NPY5DTVCG8Q63B",
        "Events": []
    },
    {
        "Id": 177,
        "GitHubFileId": "01JDEF9N6EQVXERGMJE6D6ZH30",
        "Events": []
    },
    {
        "Id": 178,
        "GitHubFileId": "01JDEF9N6EESPSVYPPBMVAV8KV",
        "Events": []
    },
    {
        "Id": 179,
        "GitHubFileId": "01JDEF9N6ERZGMCGQ15NW4WYQT",
        "Events": []
    },
    {
        "Id": 180,
        "GitHubFileId": "01JDEF9N6EEV0MQQ9GDHWSYZ2R",
        "Events": []
    },
    {
        "Id": 181,
        "GitHubFileId": "01JDEF9N6EYXBT2JVZXAEHPBK6",
        "Events": []
    },
    {
        "Id": 182,
        "GitHubFileId": "01JDEF9N6EDHVCS1EQC0R5KHZW",
        "Events": []
    },
    {
        "Id": 183,
        "GitHubFileId": "01JDEF9N6EFQMXDSF5A6KRP60D",
        "Events": []
    },
    {
        "Id": 184,
        "GitHubFileId": "01JDEF9N6EA62WFVV7FWH59R8F",
        "Events": []
    },
    {
        "Id": 185,
        "GitHubFileId": "01JDEF9N6E852F7KK8YS0HTXK5",
        "Events": []
    },
    {
        "Id": 186,
        "GitHubFileId": "01JDEF9N6EN2RDNZZ2BN99HFEN",
        "Events": []
    },
    {
        "Id": 187,
        "GitHubFileId": "01JDEF9N6EADE6KHYYM7066A5H",
        "Events": []
    },
    {
        "Id": 188,
        "GitHubFileId": "01JDEF9N6EA0PH4GZ90B0Y3Q50",
        "Events": []
    },
    {
        "Id": 189,
        "GitHubFileId": "01JDEF9N6EEZQ9T5VKF984EDDB",
        "Events": []
    },
    {
        "Id": 190,
        "GitHubFileId": "01JDEF9N6EE4JKYY77X5T6FSZP",
        "Events": []
    },
    {
        "Id": 191,
        "GitHubFileId": "01JDEF9N6E1H5ANXDBM31XCAGE",
        "Events": []
    },
    {
        "Id": 192,
        "GitHubFileId": "01JDEF9N6E7A4F08KVT87N06DX",
        "Events": []
    },
    {
        "Id": 193,
        "GitHubFileId": "01JDEF9N6EVPQQTS73PFBSW775",
        "Events": []
    },
    {
        "Id": 194,
        "GitHubFileId": "01JDEF9N6EA1SFVZKQ6T2G496R",
        "Events": []
    },
    {
        "Id": 195,
        "GitHubFileId": "01JDEF9N6E7N29130EK8WKJ77A",
        "Events": []
    },
    {
        "Id": 196,
        "GitHubFileId": "01JDEF9N6EY9GFW0P4NTQECKPX",
        "Events": []
    },
    {
        "Id": 197,
        "GitHubFileId": "01JDEF9N6E80FHYT9WZMK18TKT",
        "Events": []
    },
    {
        "Id": 198,
        "GitHubFileId": "01JDEF9N6EXHHEDM511PRN9TQC",
        "Events": []
    },
    {
        "Id": 199,
        "GitHubFileId": "01JDEF9N6E6W3ZJ3KEZJM0KNAZ",
        "Events": []
    },
    {
        "Id": 200,
        "GitHubFileId": "01JDEF9N6ER33174BWPBEB3A9G",
        "Events": []
    },
    {
        "Id": 201,
        "GitHubFileId": "01JDEF9N6EKW1BKD3865T0NMJ5",
        "Events": []
    },
    {
        "Id": 202,
        "GitHubFileId": "01JDEF9N6E9NRTCWYDVQYVEPQC",
        "Events": []
    },
    {
        "Id": 203,
        "GitHubFileId": "01JDEF9N6EYRDCCMR7Y7KX1FBH",
        "Events": []
    },
    {
        "Id": 204,
        "GitHubFileId": "01JDEF9N6EKVKRMPPZ5V3YT49E",
        "Events": []
    },
    {
        "Id": 205,
        "GitHubFileId": "01JDEF9N6EGPKFFS71Y4MF7S2W",
        "Events": []
    },
    {
        "Id": 206,
        "GitHubFileId": "01JDEF9N6EQ0B9T1G87DDHFAVB",
        "Events": []
    },
    {
        "Id": 207,
        "GitHubFileId": "01JDEF9N6EQ76K22699G335TM1",
        "Events": []
    },
    {
        "Id": 208,
        "GitHubFileId": "01JDEF9N6E74VARJW8WSQ24S8G",
        "Events": []
    },
    {
        "Id": 209,
        "GitHubFileId": "01JDEF9N6ECB5XYXMGABSWTYJG",
        "Events": []
    },
    {
        "Id": 210,
        "GitHubFileId": "01JDEF9N6ETD642SBJS6BA22ZR",
        "Events": []
    },
    {
        "Id": 211,
        "GitHubFileId": "01JDEF9N6EMFJKKCEGTK8SEW9F",
        "Events": []
    },
    {
        "Id": 212,
        "GitHubFileId": "01JDEF9N6ENXMQ13S7G12305VF",
        "Events": []
    },
    {
        "Id": 213,
        "GitHubFileId": "01JDEF9N6EDF3X5NZ8WY6BG6MT",
        "Events": []
    },
    {
        "Id": 214,
        "GitHubFileId": "01JDEF9N6E9QZP3RT1P9W4SARH",
        "Events": []
    },
    {
        "Id": 215,
        "GitHubFileId": "01JDEF9N6ES05VZ4D3J92X1BFK",
        "Events": []
    },
    {
        "Id": 216,
        "GitHubFileId": "01JDEF9N6EK3XG637QBC11BE4E",
        "Events": []
    },
    {
        "Id": 217,
        "GitHubFileId": "01JDEF9N6E0MTNWAG8Q00Y2RNZ",
        "Events": []
    },
    {
        "Id": 218,
        "GitHubFileId": "01JDEF9N6EVG5TWHJZ275MX8R4",
        "Events": []
    },
    {
        "Id": 219,
        "GitHubFileId": "01JDEF9N6EMSQZHXJKM9C3Y6Y2",
        "Events": []
    },
    {
        "Id": 220,
        "GitHubFileId": "01JDEF9N6EQNF3VR8Y3AZX8N1Y",
        "Events": []
    },
    {
        "Id": 221,
        "GitHubFileId": "01JDEF9N6EGB4CD2EZCVK90Y8E",
        "Events": []
    },
    {
        "Id": 222,
        "GitHubFileId": "01JDEF9N6EEFKXRT7TGV0N7HK6",
        "Events": []
    },
    {
        "Id": 223,
        "GitHubFileId": "01JDEF9N6EVZGXHBTJJ3S8WDQK",
        "Events": []
    },
    {
        "Id": 224,
        "GitHubFileId": "01JDEF9N6EF70ME88XP723X1TA",
        "Events": []
    },
    {
        "Id": 225,
        "GitHubFileId": "01JDEF9N6E0S22A7ZCFQ736DW7",
        "Events": []
    },
    {
        "Id": 226,
        "GitHubFileId": "01JDEF9N6ECDYCA088A523XHTC",
        "Events": []
    },
    {
        "Id": 227,
        "GitHubFileId": "01JDEF9N6E6HKWNNFRVF9WNMW8",
        "Events": []
    },
    {
        "Id": 228,
        "GitHubFileId": "01JDEF9N6ETBWNMBM146T24YT2",
        "Events": []
    },
    {
        "Id": 229,
        "GitHubFileId": "01JDEF9N6EBE48KD52W1GWGPCN",
        "Events": []
    },
    {
        "Id": 230,
        "GitHubFileId": "01JDEF9N6EE46EQ9WJ46CRJHQ9",
        "Events": []
    },
    {
        "Id": 231,
        "GitHubFileId": "01JDEF9N6ER8SEP18QQ0TS7AAS",
        "Events": []
    },
    {
        "Id": 232,
        "GitHubFileId": "01JDEF9N6EJCXANPS18SMQ4X8Y",
        "Events": []
    },
    {
        "Id": 233,
        "GitHubFileId": "01JDEF9N6ENNMB45SKZ1DB7TTB",
        "Events": []
    },
    {
        "Id": 234,
        "GitHubFileId": "01JDEF9N6ETM9EJ64AFTCY9AM8",
        "Events": []
    },
    {
        "Id": 235,
        "GitHubFileId": "01JDEF9N6EBYQXZ9KYTSC3F5R6",
        "Events": []
    },
    {
        "Id": 236,
        "GitHubFileId": "01JDEF9N6EQDFQNEBR7WBV0J6R",
        "Events": []
    },
    {
        "Id": 237,
        "GitHubFileId": "01JDEF9N6EF2B2TZEM9VDC4MPB",
        "Events": []
    },
    {
        "Id": 238,
        "GitHubFileId": "01JDEF9N6EV2F23TE48PB0YT33",
        "Events": []
    },
    {
        "Id": 239,
        "GitHubFileId": "01JDEF9N6EKPGTMXHN3324C5TN",
        "Events": []
    },
    {
        "Id": 240,
        "GitHubFileId": "01JDEF9N6EQDJAF9XDTQGA2FDK",
        "Events": []
    },
    {
        "Id": 241,
        "GitHubFileId": "01JDEF9N6E3Q5VZ236V5D24G6G",
        "Events": []
    },
    {
        "Id": 242,
        "GitHubFileId": "01JDEF9N6EAK3255J9VRVA5J74",
        "Events": []
    },
    {
        "Id": 243,
        "GitHubFileId": "01JDEF9N6EC739ME58ZTTJCNFC",
        "Events": []
    },
    {
        "Id": 244,
        "GitHubFileId": "01JDEF9N6EM0QXYH69WSGV0R4M",
        "Events": []
    },
    {
        "Id": 245,
        "GitHubFileId": "01JDEF9N6ES8F7ETCAGQ6PEV4H",
        "Events": []
    },
    {
        "Id": 246,
        "GitHubFileId": "01JDEF9N6EKT6VYVKWVT4E86W1",
        "Events": []
    },
    {
        "Id": 247,
        "GitHubFileId": "01JDEF9N6EMWA88QRPP4CMTE3V",
        "Events": []
    },
    {
        "Id": 248,
        "GitHubFileId": "01JDEF9N6E9A0NGNN0NS1ZQRJH",
        "Events": []
    },
    {
        "Id": 249,
        "GitHubFileId": "01JDEF9N6EWMZR7E0C7WKJP9P7",
        "Events": []
    },
    {
        "Id": 250,
        "GitHubFileId": "01JDEF9N6EFX8RGZ0NX2FQFSAR",
        "Events": []
    },
    {
        "Id": 251,
        "GitHubFileId": "01JDEF9N6E2HPPFMAH2KDCS1RF",
        "Events": []
    },
    {
        "Id": 252,
        "GitHubFileId": "01JDEF9N6EARZ5S2BV6BHFDA6F",
        "Events": []
    },
    {
        "Id": 253,
        "GitHubFileId": "01JDEF9N6ESZW01FDKSVW0D4ZM",
        "Events": []
    },
    {
        "Id": 254,
        "GitHubFileId": "01JDEF9N6EKT5KSDD6DGFVGEGT",
        "Events": []
    },
    {
        "Id": 255,
        "GitHubFileId": "01JDEF9N6E57AGJ194K4WRXFDN",
        "Events": []
    },
    {
        "Id": 256,
        "GitHubFileId": "01JDEF9N6ES4974RVTCBY9VFPC",
        "Events": []
    },
    {
        "Id": 257,
        "GitHubFileId": "01JDEF9N6EKXZWEQFYKE9DYMTF",
        "Events": []
    },
    {
        "Id": 258,
        "GitHubFileId": "01JDEF9N6E33BFBQPMT909EAW1",
        "Events": []
    },
    {
        "Id": 259,
        "GitHubFileId": "01JDEF9N6EMZWV5SWM1Q5KNYB1",
        "Events": []
    },
    {
        "Id": 260,
        "GitHubFileId": "01JDEF9N6E5Q6R1TGKS9Y74P08",
        "Events": []
    },
    {
        "Id": 261,
        "GitHubFileId": "01JDEF9N6ETNCRSSMDW34WBGRX",
        "Events": []
    },
    {
        "Id": 262,
        "GitHubFileId": "01JDEF9N6EVJFY8G2MYV30DBPK",
        "Events": []
    },
    {
        "Id": 263,
        "GitHubFileId": "01JDEF9N6EZM44DEDS13A2Y7TK",
        "Events": []
    },
    {
        "Id": 264,
        "GitHubFileId": "01JDEF9N6ESCMEV84PXQ08QWDF",
        "Events": []
    },
    {
        "Id": 265,
        "GitHubFileId": "01JDEF9N6E0TTSVCC457JM72YR",
        "Events": []
    },
    {
        "Id": 266,
        "GitHubFileId": "01JDEF9N6E4A8T5W42GYC8PR9F",
        "Events": []
    },
    {
        "Id": 267,
        "GitHubFileId": "01JDEF9N6EYBE20ZHMT4CQJ53A",
        "Events": []
    },
    {
        "Id": 268,
        "GitHubFileId": "01JDEF9N6EJZNREKF99N010QKC",
        "Events": []
    },
    {
        "Id": 269,
        "GitHubFileId": "01JDEF9N6ER0MJ82J6KRMQKHQR",
        "Events": []
    },
    {
        "Id": 270,
        "GitHubFileId": "01JDEF9N6EN2WHW3B13CDME7T0",
        "Events": []
    },
    {
        "Id": 271,
        "GitHubFileId": "01JDEF9N6EVXRH0PTP72TPAM42",
        "Events": []
    },
    {
        "Id": 272,
        "GitHubFileId": "01JDEF9N6EZ5QF0W3TWHQMVA5H",
        "Events": []
    },
    {
        "Id": 273,
        "GitHubFileId": "01JDEF9N6EYJMXTBJTJQ6HSZXV",
        "Events": []
    },
    {
        "Id": 274,
        "GitHubFileId": "01JDEF9N6EZNK73ACB02MEDH3D",
        "Events": []
    },
    {
        "Id": 275,
        "GitHubFileId": "01JDEF9N6EF6ZBGMVNAE8K7ZVQ",
        "Events": []
    },
    {
        "Id": 276,
        "GitHubFileId": "01JDEF9N6EZXGK0MJ8VT54J2MS",
        "Events": []
    },
    {
        "Id": 277,
        "GitHubFileId": "01JDEF9N6EJNX8TR22YQ17RTRC",
        "Events": []
    },
    {
        "Id": 278,
        "GitHubFileId": "01JDEF9N6E3RFXDER5KN2FAQ6X",
        "Events": []
    },
    {
        "Id": 279,
        "GitHubFileId": "01JDEF9N6EZTY1YHVHGW3AN0ZW",
        "Events": []
    },
    {
        "Id": 280,
        "GitHubFileId": "01JDEF9N6EZCGSACJ0AHD8W59S",
        "Events": []
    },
    {
        "Id": 281,
        "GitHubFileId": "01JDEF9N6EN5AAKS1QKVN4T5BP",
        "Events": []
    },
    {
        "Id": 282,
        "GitHubFileId": "01JDEF9N6EY5968ZC4KMY66R1T",
        "Events": []
    },
    {
        "Id": 283,
        "GitHubFileId": "01JDEF9N6E0C98M7EAAFV0RBH0",
        "Events": []
    },
    {
        "Id": 284,
        "GitHubFileId": "01JDEF9N6EWTX85A596B0715DE",
        "Events": []
    },
    {
        "Id": 285,
        "GitHubFileId": "01JDEF9N6EEVBW1FMK0Z1W1EEB",
        "Events": []
    },
    {
        "Id": 286,
        "GitHubFileId": "01JDEF9N6ENZWFGH3AN32YY2XY",
        "Events": []
    },
    {
        "Id": 287,
        "GitHubFileId": "01JDEF9N6EWJE972H3K2GX8VBB",
        "Events": []
    },
    {
        "Id": 288,
        "GitHubFileId": "01JDEF9N6EE8R7C51D2RW3AQH9",
        "Events": []
    },
    {
        "Id": 289,
        "GitHubFileId": "01JDEF9N6EW5YEEG0WBYVXK045",
        "Events": []
    },
    {
        "Id": 290,
        "GitHubFileId": "01JDEF9N6EFTPQF4XS1J5T5SD2",
        "Events": []
    },
    {
        "Id": 291,
        "GitHubFileId": "01JDEF9N6EWC85628DP0T56QFY",
        "Events": []
    },
    {
        "Id": 292,
        "GitHubFileId": "01JDEF9N6E0FJF2DCMXP9NB2MY",
        "Events": []
    },
    {
        "Id": 293,
        "GitHubFileId": "01JDEF9N6E2W59FKAN9C6YRX9X",
        "Events": []
    },
    {
        "Id": 294,
        "GitHubFileId": "01JDEF9N6EJKFSW0W6JX2PZSK7",
        "Events": []
    },
    {
        "Id": 295,
        "GitHubFileId": "01JDEF9N6EF27P31P8TPMVA9ES",
        "Events": []
    },
    {
        "Id": 296,
        "GitHubFileId": "01JDEF9N6E79SMTEV60K4AVHN6",
        "Events": []
    },
    {
        "Id": 297,
        "GitHubFileId": "01JDEF9N6E0CG966C1M6Y2ZB1W",
        "Events": []
    },
    {
        "Id": 298,
        "GitHubFileId": "01JDEF9N6EZDB6XR0J4R64NKHD",
        "Events": []
    },
    {
        "Id": 299,
        "GitHubFileId": "01JDEF9N6E0NKBEHZBSSDJSN4D",
        "Events": []
    },
    {
        "Id": 300,
        "GitHubFileId": "01JDEF9N6EF4W7QG7YN18KWKMZ",
        "Events": []
    },
    {
        "Id": 301,
        "GitHubFileId": "01JDEF9N6EGMS3V1QVHNC51Q8Y",
        "Events": []
    },
    {
        "Id": 302,
        "GitHubFileId": "01JDEF9N6EY620YQDXP2A63HAP",
        "Events": []
    },
    {
        "Id": 303,
        "GitHubFileId": "01JDEF9N6ECB9X6S4GYG9WX9G3",
        "Events": []
    },
    {
        "Id": 304,
        "GitHubFileId": "01JDEF9N6EANEEWQV9C4ZHYE44",
        "Events": []
    },
    {
        "Id": 305,
        "GitHubFileId": "01JDEF9N6EQ95Q34JBRYCEFS55",
        "Events": []
    },
    {
        "Id": 306,
        "GitHubFileId": "01JDEF9N6EMKNVGPJ5JS533249",
        "Events": []
    },
    {
        "Id": 307,
        "GitHubFileId": "01JDEF9N6EQDSASAPXCPPKBMWP",
        "Events": []
    },
    {
        "Id": 308,
        "GitHubFileId": "01JDEF9N6ET9W5MAA02GTBM9V4",
        "Events": []
    },
    {
        "Id": 309,
        "GitHubFileId": "01JDEF9N6E32QCKBPZP675T94Q",
        "Events": []
    },
    {
        "Id": 310,
        "GitHubFileId": "01JDEF9N6E5K741E0KMVM52HW1",
        "Events": []
    },
    {
        "Id": 311,
        "GitHubFileId": "01JDEF9N6EHHZN1AGR2RHJVEAX",
        "Events": []
    },
    {
        "Id": 312,
        "GitHubFileId": "01JDEF9N6EJ6J6FSD58RCYVR9P",
        "Events": []
    },
    {
        "Id": 313,
        "GitHubFileId": "01JDEF9N6E9HYT2APGT3CPYBTW",
        "Events": []
    },
    {
        "Id": 314,
        "GitHubFileId": "01JDEF9N6EKGC3E743KGDQMM4N",
        "Events": []
    },
    {
        "Id": 315,
        "GitHubFileId": "01JDEF9N6E6J0VJ2P0ZK73ZMC4",
        "Events": []
    },
    {
        "Id": 316,
        "GitHubFileId": "01JDEF9N6EJ8T2SXAHBRV34FZG",
        "Events": []
    },
    {
        "Id": 317,
        "GitHubFileId": "01JDEF9N6EKMVA2ZBJHA76MBR7",
        "Events": []
    },
    {
        "Id": 318,
        "GitHubFileId": "01JDEF9N6EEW5TZE0Y4XRZZ7QS",
        "Events": []
    },
    {
        "Id": 319,
        "GitHubFileId": "01JDEF9N6EB37AKPMR4GK6FH2B",
        "Events": []
    },
    {
        "Id": 320,
        "GitHubFileId": "01JDEF9N6EXVT2Z7NJD61ZM63R",
        "Events": []
    },
    {
        "Id": 321,
        "GitHubFileId": "01JDEF9N6EDFVWNB82RS0V3DJV",
        "Events": []
    },
    {
        "Id": 322,
        "GitHubFileId": "01JDEF9N6EXVHA8XJ0VMWFVXPQ",
        "Events": []
    },
    {
        "Id": 323,
        "GitHubFileId": "01JDEF9N6E6TCVEHKKY9351FB3",
        "Events": []
    },
    {
        "Id": 324,
        "GitHubFileId": "01JDEF9N6E77TGT3Q830RP3ERR",
        "Events": []
    },
    {
        "Id": 325,
        "GitHubFileId": "01JDEF9N6E15ZZ9259T8V9FZYH",
        "Events": []
    },
    {
        "Id": 326,
        "GitHubFileId": "01JDEF9N6E1Q2ES93K728EXDSZ",
        "Events": []
    },
    {
        "Id": 327,
        "GitHubFileId": "01JDEF9N6E0M18B43B564523ZX",
        "Events": []
    },
    {
        "Id": 328,
        "GitHubFileId": "01JDEF9N6EXJ1XCRXYKE4H3RHQ",
        "Events": [
            {
                "Title": "",
                "Start": "2024-11-23T12:00:00",
                "End": "2024-11-23T17:00:00"
            }
        ]
    },
    {
        "Id": 329,
        "GitHubFileId": "01JDEF9N6E2B7K2RWJ3T39P642",
        "Events": []
    },
    {
        "Id": 330,
        "GitHubFileId": "01JDEF9N6E9GNCN0JPR4EFAT47",
        "Events": []
    },
    {
        "Id": 331,
        "GitHubFileId": "01JDEF9N6E77PC2PNPJ31AQADP",
        "Events": []
    },
    {
        "Id": 332,
        "GitHubFileId": "01JDEF9N6EVKVN1PZX8QWQHHF4",
        "Events": []
    },
    {
        "Id": 333,
        "GitHubFileId": "01JDEF9N6ED7XWWNT8Z4WCETWV",
        "Events": []
    },
    {
        "Id": 334,
        "GitHubFileId": "01JDEF9N6E2R0X6V71JB1J6831",
        "Events": []
    },
    {
        "Id": 335,
        "GitHubFileId": "01JDEF9N6ET4QF4QGBZ07XVKJN",
        "Events": []
    },
    {
        "Id": 336,
        "GitHubFileId": "01JDEF9N6EW7TP75BMCYQ5P6YE",
        "Events": []
    },
    {
        "Id": 337,
        "GitHubFileId": "01JDEF9N6EY6XX11DGE97R8T18",
        "Events": []
    },
    {
        "Id": 338,
        "GitHubFileId": "01JDEF9N6EWRA5AMFWGPYXMY0E",
        "Events": []
    },
    {
        "Id": 339,
        "GitHubFileId": "01JDEF9N6EN08MNDASFZVZAM9M",
        "Events": []
    },
    {
        "Id": 340,
        "GitHubFileId": "01JDEF9N6ERB8XMWC331NBGBTE",
        "Events": []
    },
    {
        "Id": 341,
        "GitHubFileId": "01JDEF9N6E2G0X2G37HD3HCFNP",
        "Events": []
    },
    {
        "Id": 342,
        "GitHubFileId": "01JDEF9N6ERN5H35KMMSTZHEGS",
        "Events": []
    },
    {
        "Id": 343,
        "GitHubFileId": "01JDEF9N6EBT0WKXMACW0KHFWP",
        "Events": []
    },
    {
        "Id": 344,
        "GitHubFileId": "01JDEF9N6EG3N5AG200B67F9KA",
        "Events": []
    },
    {
        "Id": 345,
        "GitHubFileId": "01JDEF9N6EW1DFA1429Y4MMMQS",
        "Events": []
    },
    {
        "Id": 346,
        "GitHubFileId": "01JDEF9N6E98Z4EDZ5S2AG7YKZ",
        "Events": []
    },
    {
        "Id": 347,
        "GitHubFileId": "01JDEF9N6EHPNKQNJZB5NGX3YZ",
        "Events": []
    },
    {
        "Id": 348,
        "GitHubFileId": "01JDEF9N6EVT8P2FEYV8WXY5GT",
        "Events": []
    },
    {
        "Id": 349,
        "GitHubFileId": "01JDEF9N6EMXPQHT75FZW85PN9",
        "Events": []
    },
    {
        "Id": 350,
        "GitHubFileId": "01JDEF9N6EJ9E1HADV49C1YV0R",
        "Events": []
    },
    {
        "Id": 351,
        "GitHubFileId": "01JDEF9N6EHA9626R09MCD0FRM",
        "Events": []
    },
    {
        "Id": 352,
        "GitHubFileId": "01JDEF9N6E6GPYYJ8E7DBBQE72",
        "Events": []
    },
    {
        "Id": 353,
        "GitHubFileId": "01JDEF9N6E62NTKRRGWJ7CDYQ3",
        "Events": []
    },
    {
        "Id": 354,
        "GitHubFileId": "01JDEF9N6EP83XT50RGCEAQPJN",
        "Events": []
    },
    {
        "Id": 355,
        "GitHubFileId": "01JDEF9N6EC3SM3XESWGEV82PH",
        "Events": []
    },
    {
        "Id": 356,
        "GitHubFileId": "01JDEF9N6EDD256MY3X8M541V9",
        "Events": []
    },
    {
        "Id": 357,
        "GitHubFileId": "01JDEF9N6ENS7Y571HCKXGE447",
        "Events": []
    },
    {
        "Id": 358,
        "GitHubFileId": "01JDEF9N6E2J95HQ5MPH63YVW5",
        "Events": []
    },
    {
        "Id": 359,
        "GitHubFileId": "01JDEF9N6E42ETDF1TGZ740EJ6",
        "Events": []
    },
    {
        "Id": 360,
        "GitHubFileId": "01JDEF9N6ET7EWPDJKA21990P0",
        "Events": []
    },
    {
        "Id": 361,
        "GitHubFileId": "01JDEF9N6ECAVY2ME43QZ1KCJ5",
        "Events": []
    },
    {
        "Id": 362,
        "GitHubFileId": "01JDEF9N6E65BXDMRZDSY2XQQ4",
        "Events": []
    },
    {
        "Id": 363,
        "GitHubFileId": "01JDEF9N6ESB1NKDCMTWNPXM2D",
        "Events": []
    },
    {
        "Id": 364,
        "GitHubFileId": "01JDEF9N6ETQZ9YJSHBHC0WKKZ",
        "Events": []
    },
    {
        "Id": 365,
        "GitHubFileId": "01JDEF9N6EBQ72V24311H2DGYA",
        "Events": []
    },
    {
        "Id": 366,
        "GitHubFileId": "01JDEF9N6EC8YT8WMR0EAE9KH9",
        "Events": []
    }
]